<annotation verified="yes">
	<folder>JPEGImages</folder>
	<filename>cw0061.png</filename>
	<path>C:\Users\13160\Desktop\VOCdevkit\VOC2007\JPEGImages\cw0061.png</path>
	<source>
		<database>Unknown</database>
	</source>
	<size>
		<width>512</width>
		<height>512</height>
		<depth>3</depth>
	</size>
	<segmented>0</segmented>
	<object>
		<name>cw</name>
		<pose>Unspecified</pose>
		<truncated>0</truncated>
		<difficult>0</difficult>
		<bndbox>
			<xmin>253</xmin>
			<ymin>88</ymin>
			<xmax>498</xmax>
			<ymax>264</ymax>
		</bndbox>
	</object>
	<object>
		<name>cw</name>
		<pose>Unspecified</pose>
		<truncated>0</truncated>
		<difficult>0</difficult>
		<bndbox>
			<xmin>469</xmin>
			<ymin>276</ymin>
			<xmax>511</xmax>
			<ymax>503</ymax>
		</bndbox>
	</object>
</annotation>
