<annotation verified="yes">
	<folder>img</folder>
	<filename>tp0064.png</filename>
	<path>C:\Users\13160\Desktop\tp\img\tp064.png</path>
	<source>
		<database>Unknown</database>
	</source>
	<size>
		<width>512</width>
		<height>512</height>
		<depth>3</depth>
	</size>
	<segmented>0</segmented>
	<object>
		<name>tp</name>
		<pose>Unspecified</pose>
		<truncated>0</truncated>
		<difficult>0</difficult>
		<bndbox>
			<xmin>175</xmin>
			<ymin>258</ymin>
			<xmax>453</xmax>
			<ymax>334</ymax>
		</bndbox>
	</object>
</annotation>